pyunit_plate/__init__.py
pyunit_plate/__init__.pyc
pyunit_plate/plate.py
pyunit_plate/rules.py
pyunit_plate/农用车牌.json
pyunit_plate/民用车牌.json
pyunit_plate-2020.6.17.dist-info/METADATA
pyunit_plate-2020.6.17.dist-info/WHEEL
pyunit_plate-2020.6.17.dist-info/top_level.txt
pyunit_plate-2020.6.17.dist-info/RECORD
