Metadata-Version: 2.1
Name: pyunit-plate
Version: 2020.6.17
Summary: 各种各样车牌号规则提取
Home-page: https://github.com/PyUnit/pyunit-plate
Author: Jtyoui
Author-email: jtyoui@qq.com
License: MIT Licence
Platform: any
Classifier: Programming Language :: Python :: 3
Classifier: License :: OSI Approved :: MIT License
Classifier: Operating System :: OS Independent
